{"years": [{"year": 1999, "imports": [{"name": "Manufactures", "id": "manuf", "percent": 73.2129}, {"name": "Food Products", "id": "16-24_FoodProd", "percent": 5.5751}, {"name": "Miscellaneous", "id": "90-99_Miscellan", "percent": 2.04}, {"name": "Chemicals", "id": "28-38_Chemicals", "percent": 1.6837}, {"name": "Animal", "id": "01-05_Animal", "percent": 2.0208}, {"name": "Ores and Metals", "id": "OresMtls", "percent": 0.614}, {"name": "Footwear", "id": "64-67_Footwear", "percent": 0.1717}, {"name": "Textiles and Clothing", "id": "50-63_TextCloth", "percent": 0.549}, {"name": "All Products", "id": "Total", "percent": 100}, {"name": "Plastic or Rubber", "id": "39-40_PlastiRub", "percent": 1.4362}, {"name": "Textiles", "id": "Textiles", "percent": 0.5652}, {"name": "Mach and Elec", "id": "84-85_MachElec", "percent": 8.7194}, {"name": "Agricultural Raw Materials", "id": "AgrRaw", "percent": 0.1938}, {"name": "Metals", "id": "72-83_Metals", "percent": 3.0993}, {"name": "Fuels", "id": "27-27_Fuels", "percent": 8.7465}, {"name": "Machinery and Transport Equipment", "id": "Transp", "percent": 59.4869}, {"name": "Fuel", "id": "Fuels", "percent": 8.2373}, {"name": "Hides and Skins", "id": "41-43_HidesSkin", "percent": 0.0066}, {"name": "Raw materials", "id": "UNCTAD-SoP1", "percent": 2.5665}, {"name": "Transportation", "id": "86-89_Transport", "percent": 50.6084}, {"name": "Vegetable", "id": "06-15_Vegetable", "percent": 10.1751}, {"name": "Minerals", "id": "25-26_Minerals", "percent": 3.4904}, {"name": "Capital goods", "id": "UNCTAD-SoP4", "percent": 10.0245}, {"name": "Stone and Glass", "id": "68-71_StoneGlas", "percent": 1.2501}, {"name": "Consumer goods", "id": "UNCTAD-SoP3", "percent": 71.4797}, {"name": "Food", "id": "Food", "percent": 17.7402}, {"name": "Chemical", "id": "Chemical", "percent": 1.9587}, {"name": "Intermediate goods", "id": "UNCTAD-SoP2", "percent": 15.926}, {"name": "Wood", "id": "44-49_Wood", "percent": 0.4277}], "exports": [{"name": "Manufactures", "id": "manuf", "percent": 1.4007}, {"name": "Food Products", "id": "16-24_FoodProd", "percent": 96.2629}, {"name": "Chemicals", "id": "28-38_Chemicals", "percent": 0.0424}, {"name": "Animal", "id": "01-05_Animal", "percent": 1.1661}, {"name": "All Products", "id": "Total", "percent": 100}, {"name": "Mach and Elec", "id": "84-85_MachElec", "percent": 0.8445}, {"name": "Metals", "id": "72-83_Metals", "percent": 0.0996}, {"name": "Machinery and Transport Equipment", "id": "Transp", "percent": 1.2303}, {"name": "Raw materials", "id": "UNCTAD-SoP1", "percent": 94.667}, {"name": "Transportation", "id": "86-89_Transport", "percent": 0.3857}, {"name": "Vegetable", "id": "06-15_Vegetable", "percent": 1.1703}, {"name": "Capital goods", "id": "UNCTAD-SoP4", "percent": 0.8958}, {"name": "Consumer goods", "id": "UNCTAD-SoP3", "percent": 4.0453}, {"name": "Food", "id": "Food", "percent": 98.5993}, {"name": "Intermediate goods", "id": "UNCTAD-SoP2", "percent": 0.3919}, {"name": "Wood", "id": "44-49_Wood", "percent": 0.0285}]}, {"year": 2000, "imports": [{"name": "Manufactures", "id": "manuf", "percent": 56.7346}, {"name": "Food Products", "id": "16-24_FoodProd", "percent": 14.2998}, {"name": "Miscellaneous", "id": "90-99_Miscellan", "percent": 1.1275}, {"name": "Chemicals", "id": "28-38_Chemicals", "percent": 3.0412}, {"name": "Animal", "id": "01-05_Animal", "percent": 1.9636}, {"name": "Ores and Metals", "id": "OresMtls", "percent": 0.6736}, {"name": "Footwear", "id": "64-67_Footwear", "percent": 0.9763}, {"name": "Textiles and Clothing", "id": "50-63_TextCloth", "percent": 7.1473}, {"name": "All Products", "id": "Total", "percent": 100}, {"name": "Plastic or Rubber", "id": "39-40_PlastiRub", "percent": 2.5986}, {"name": "Textiles", "id": "Textiles", "percent": 8.2968}, {"name": "Mach and Elec", "id": "84-85_MachElec", "percent": 20.2298}, {"name": "Agricultural Raw Materials", "id": "AgrRaw", "percent": 0.408}, {"name": "Metals", "id": "72-83_Metals", "percent": 4.5688}, {"name": "Fuels", "id": "27-27_Fuels", "percent": 11.0164}, {"name": "Machinery and Transport Equipment", "id": "Transp", "percent": 30.4617}, {"name": "Fuel", "id": "Fuels", "percent": 10.8179}, {"name": "Hides and Skins", "id": "41-43_HidesSkin", "percent": 0.7558}, {"name": "Raw materials", "id": "UNCTAD-SoP1", "percent": 7.2041}, {"name": "Transportation", "id": "86-89_Transport", "percent": 10.388}, {"name": "Vegetable", "id": "06-15_Vegetable", "percent": 14.6529}, {"name": "Minerals", "id": "25-26_Minerals", "percent": 3.4822}, {"name": "Capital goods", "id": "UNCTAD-SoP4", "percent": 24.0137}, {"name": "Stone and Glass", "id": "68-71_StoneGlas", "percent": 2.9198}, {"name": "Consumer goods", "id": "UNCTAD-SoP3", "percent": 52.4846}, {"name": "Food", "id": "Food", "percent": 30.8234}, {"name": "Chemical", "id": "Chemical", "percent": 2.8076}, {"name": "Intermediate goods", "id": "UNCTAD-SoP2", "percent": 15.764}, {"name": "Wood", "id": "44-49_Wood", "percent": 0.832}], "exports": [{"name": "Manufactures", "id": "manuf", "percent": 2.5964}, {"name": "Food Products", "id": "16-24_FoodProd", "percent": 91.2473}, {"name": "Miscellaneous", "id": "90-99_Miscellan", "percent": 0.01}, {"name": "Chemicals", "id": "28-38_Chemicals", "percent": 0.4134}, {"name": "Ores and Metals", "id": "OresMtls", "percent": 0.0147}, {"name": "Textiles and Clothing", "id": "50-63_TextCloth", "percent": 0.0102}, {"name": "All Products", "id": "Total", "percent": 100}, {"name": "Plastic or Rubber", "id": "39-40_PlastiRub", "percent": 0.1733}, {"name": "Textiles", "id": "Textiles", "percent": 0.0102}, {"name": "Mach and Elec", "id": "84-85_MachElec", "percent": 1.5812}, {"name": "Agricultural Raw Materials", "id": "AgrRaw", "percent": 0.0972}, {"name": "Metals", "id": "72-83_Metals", "percent": 0.2345}, {"name": "Machinery and Transport Equipment", "id": "Transp", "percent": 1.7488}, {"name": "Raw materials", "id": "UNCTAD-SoP1", "percent": 94.1245}, {"name": "Transportation", "id": "86-89_Transport", "percent": 0.1675}, {"name": "Vegetable", "id": "06-15_Vegetable", "percent": 5.695}, {"name": "Capital goods", "id": "UNCTAD-SoP4", "percent": 1.7289}, {"name": "Stone and Glass", "id": "68-71_StoneGlas", "percent": 0.2185}, {"name": "Consumer goods", "id": "UNCTAD-SoP3", "percent": 2.4085}, {"name": "Food", "id": "Food", "percent": 96.9212}, {"name": "Chemical", "id": "Chemical", "percent": 0.0441}, {"name": "Intermediate goods", "id": "UNCTAD-SoP2", "percent": 1.3676}, {"name": "Wood", "id": "44-49_Wood", "percent": 0.2488}]}, {"year": 2001, "imports": [{"name": "Manufactures", "id": "manuf", "percent": 47.3687}, {"name": "Food Products", "id": "16-24_FoodProd", "percent": 17.8107}, {"name": "Miscellaneous", "id": "90-99_Miscellan", "percent": 2.1814}, {"name": "Chemicals", "id": "28-38_Chemicals", "percent": 4.4808}, {"name": "Animal", "id": "01-05_Animal", "percent": 2.9588}, {"name": "Ores and Metals", "id": "OresMtls", "percent": 1.3327}, {"name": "Footwear", "id": "64-67_Footwear", "percent": 0.4145}, {"name": "Textiles and Clothing", "id": "50-63_TextCloth", "percent": 2.0579}, {"name": "All Products", "id": "Total", "percent": 100}, {"name": "Plastic or Rubber", "id": "39-40_PlastiRub", "percent": 2.2743}, {"name": "Textiles", "id": "Textiles", "percent": 2.0702}, {"name": "Mach and Elec", "id": "84-85_MachElec", "percent": 8.7918}, {"name": "Agricultural Raw Materials", "id": "AgrRaw", "percent": 0.3368}, {"name": "Metals", "id": "72-83_Metals", "percent": 4.3351}, {"name": "Fuels", "id": "27-27_Fuels", "percent": 14.9251}, {"name": "Machinery and Transport Equipment", "id": "Transp", "percent": 23.6296}, {"name": "Fuel", "id": "Fuels", "percent": 14.3497}, {"name": "Hides and Skins", "id": "41-43_HidesSkin", "percent": 0.0327}, {"name": "Raw materials", "id": "UNCTAD-SoP1", "percent": 4.3566}, {"name": "Transportation", "id": "86-89_Transport", "percent": 14.7888}, {"name": "Vegetable", "id": "06-15_Vegetable", "percent": 15.8366}, {"name": "Minerals", "id": "25-26_Minerals", "percent": 6.0985}, {"name": "Capital goods", "id": "UNCTAD-SoP4", "percent": 10.2241}, {"name": "Stone and Glass", "id": "68-71_StoneGlas", "percent": 2.4099}, {"name": "Consumer goods", "id": "UNCTAD-SoP3", "percent": 66.2544}, {"name": "Food", "id": "Food", "percent": 36.5823}, {"name": "Chemical", "id": "Chemical", "percent": 4.5433}, {"name": "Intermediate goods", "id": "UNCTAD-SoP2", "percent": 19.1555}, {"name": "Wood", "id": "44-49_Wood", "percent": 0.6031}], "exports": [{"name": "Manufactures", "id": "manuf", "percent": 1.9823}, {"name": "Food Products", "id": "16-24_FoodProd", "percent": 83.1768}, {"name": "Miscellaneous", "id": "90-99_Miscellan", "percent": 0.0173}, {"name": "Animal", "id": "01-05_Animal", "percent": 10.3274}, {"name": "Ores and Metals", "id": "OresMtls", "percent": 0.0011}, {"name": "Textiles and Clothing", "id": "50-63_TextCloth", "percent": 0.0038}, {"name": "All Products", "id": "Total", "percent": 100}, {"name": "Textiles", "id": "Textiles", "percent": 0.0038}, {"name": "Mach and Elec", "id": "84-85_MachElec", "percent": 0.1374}, {"name": "Agricultural Raw Materials", "id": "AgrRaw", "percent": 0.0227}, {"name": "Metals", "id": "72-83_Metals", "percent": 0.4407}, {"name": "Machinery and Transport Equipment", "id": "Transp", "percent": 1.5223}, {"name": "Raw materials", "id": "UNCTAD-SoP1", "percent": 96.1575}, {"name": "Transportation", "id": "86-89_Transport", "percent": 1.3849}, {"name": "Vegetable", "id": "06-15_Vegetable", "percent": 4.5079}, {"name": "Capital goods", "id": "UNCTAD-SoP4", "percent": 0.3171}, {"name": "Consumer goods", "id": "UNCTAD-SoP3", "percent": 3.0638}, {"name": "Food", "id": "Food", "percent": 97.9894}, {"name": "Intermediate goods", "id": "UNCTAD-SoP2", "percent": 0.4571}, {"name": "Wood", "id": "44-49_Wood", "percent": 0.0039}]}, {"year": 2002, "imports": [{"name": "Manufactures", "id": "manuf", "percent": 44.2572}, {"name": "Food Products", "id": "16-24_FoodProd", "percent": 19.7994}, {"name": "Miscellaneous", "id": "90-99_Miscellan", "percent": 2.4876}, {"name": "Chemicals", "id": "28-38_Chemicals", "percent": 3.8465}, {"name": "Animal", "id": "01-05_Animal", "percent": 4.3297}, {"name": "Ores and Metals", "id": "OresMtls", "percent": 1.4025}, {"name": "Footwear", "id": "64-67_Footwear", "percent": 0.3835}, {"name": "Textiles and Clothing", "id": "50-63_TextCloth", "percent": 1.9891}, {"name": "All Products", "id": "Total", "percent": 100}, {"name": "Plastic or Rubber", "id": "39-40_PlastiRub", "percent": 2.1046}, {"name": "Textiles", "id": "Textiles", "percent": 2.0122}, {"name": "Mach and Elec", "id": "84-85_MachElec", "percent": 12.9753}, {"name": "Agricultural Raw Materials", "id": "AgrRaw", "percent": 0.7896}, {"name": "Metals", "id": "72-83_Metals", "percent": 4.2065}, {"name": "Fuels", "id": "27-27_Fuels", "percent": 12.1569}, {"name": "Machinery and Transport Equipment", "id": "Transp", "percent": 24.7414}, {"name": "Fuel", "id": "Fuels", "percent": 11.7051}, {"name": "Hides and Skins", "id": "41-43_HidesSkin", "percent": 0.0445}, {"name": "Raw materials", "id": "UNCTAD-SoP1", "percent": 5.6916}, {"name": "Transportation", "id": "86-89_Transport", "percent": 11.5982}, {"name": "Vegetable", "id": "06-15_Vegetable", "percent": 17.571}, {"name": "Minerals", "id": "25-26_Minerals", "percent": 4.2957}, {"name": "Capital goods", "id": "UNCTAD-SoP4", "percent": 13.6337}, {"name": "Stone and Glass", "id": "68-71_StoneGlas", "percent": 1.4949}, {"name": "Consumer goods", "id": "UNCTAD-SoP3", "percent": 59.765}, {"name": "Food", "id": "Food", "percent": 41.6825}, {"name": "Chemical", "id": "Chemical", "percent": 3.8818}, {"name": "Intermediate goods", "id": "UNCTAD-SoP2", "percent": 20.7638}, {"name": "Wood", "id": "44-49_Wood", "percent": 0.7166}], "exports": [{"name": "Manufactures", "id": "manuf", "percent": 2.9668}, {"name": "Food Products", "id": "16-24_FoodProd", "percent": 93.3318}, {"name": "Miscellaneous", "id": "90-99_Miscellan", "percent": 0.3264}, {"name": "Chemicals", "id": "28-38_Chemicals", "percent": 0.0616}, {"name": "Animal", "id": "01-05_Animal", "percent": 1.5517}, {"name": "Textiles and Clothing", "id": "50-63_TextCloth", "percent": 0.112}, {"name": "All Products", "id": "Total", "percent": 100}, {"name": "Plastic or Rubber", "id": "39-40_PlastiRub", "percent": 0.0494}, {"name": "Textiles", "id": "Textiles", "percent": 0.1158}, {"name": "Mach and Elec", "id": "84-85_MachElec", "percent": 1.0525}, {"name": "Agricultural Raw Materials", "id": "AgrRaw", "percent": 0.0787}, {"name": "Metals", "id": "72-83_Metals", "percent": 0.1616}, {"name": "Machinery and Transport Equipment", "id": "Transp", "percent": 2.5607}, {"name": "Fuel", "id": "Fuels", "percent": 0.0001}, {"name": "Raw materials", "id": "UNCTAD-SoP1", "percent": 94.763}, {"name": "Transportation", "id": "86-89_Transport", "percent": 1.5082}, {"name": "Vegetable", "id": "06-15_Vegetable", "percent": 1.8214}, {"name": "Capital goods", "id": "UNCTAD-SoP4", "percent": 2.1713}, {"name": "Stone and Glass", "id": "68-71_StoneGlas", "percent": 0.0172}, {"name": "Consumer goods", "id": "UNCTAD-SoP3", "percent": 2.7023}, {"name": "Food", "id": "Food", "percent": 96.6288}, {"name": "Chemical", "id": "Chemical", "percent": 0.0487}, {"name": "Intermediate goods", "id": "UNCTAD-SoP2", "percent": 0.0378}, {"name": "Wood", "id": "44-49_Wood", "percent": 0.0063}]}, {"year": 2003, "imports": [{"name": "Manufactures", "id": "manuf", "percent": 49.4444}, {"name": "Food Products", "id": "16-24_FoodProd", "percent": 21.6726}, {"name": "Miscellaneous", "id": "90-99_Miscellan", "percent": 2.3192}, {"name": "Chemicals", "id": "28-38_Chemicals", "percent": 4.8725}, {"name": "Animal", "id": "01-05_Animal", "percent": 4.3793}, {"name": "Ores and Metals", "id": "OresMtls", "percent": 0.2746}, {"name": "Footwear", "id": "64-67_Footwear", "percent": 0.7414}, {"name": "Textiles and Clothing", "id": "50-63_TextCloth", "percent": 2.2166}, {"name": "All Products", "id": "Total", "percent": 100}, {"name": "Plastic or Rubber", "id": "39-40_PlastiRub", "percent": 2.8483}, {"name": "Textiles", "id": "Textiles", "percent": 2.2489}, {"name": "Mach and Elec", "id": "84-85_MachElec", "percent": 12.8664}, {"name": "Agricultural Raw Materials", "id": "AgrRaw", "percent": 0.9578}, {"name": "Metals", "id": "72-83_Metals", "percent": 5.4213}, {"name": "Fuels", "id": "27-27_Fuels", "percent": 10.8127}, {"name": "Machinery and Transport Equipment", "id": "Transp", "percent": 23.8663}, {"name": "Fuel", "id": "Fuels", "percent": 10.8389}, {"name": "Hides and Skins", "id": "41-43_HidesSkin", "percent": 0.113}, {"name": "Raw materials", "id": "UNCTAD-SoP1", "percent": 5.6812}, {"name": "Transportation", "id": "86-89_Transport", "percent": 11.021}, {"name": "Vegetable", "id": "06-15_Vegetable", "percent": 12.438}, {"name": "Minerals", "id": "25-26_Minerals", "percent": 4.0165}, {"name": "Capital goods", "id": "UNCTAD-SoP4", "percent": 16.2681}, {"name": "Stone and Glass", "id": "68-71_StoneGlas", "percent": 2.7954}, {"name": "Consumer goods", "id": "UNCTAD-SoP3", "percent": 60.017}, {"name": "Food", "id": "Food", "percent": 38.4305}, {"name": "Chemical", "id": "Chemical", "percent": 5.0069}, {"name": "Intermediate goods", "id": "UNCTAD-SoP2", "percent": 18.033}, {"name": "Wood", "id": "44-49_Wood", "percent": 1.4658}], "exports": [{"name": "Manufactures", "id": "manuf", "percent": 4.9302}, {"name": "Food Products", "id": "16-24_FoodProd", "percent": 93.4105}, {"name": "Miscellaneous", "id": "90-99_Miscellan", "percent": 0}, {"name": "Chemicals", "id": "28-38_Chemicals", "percent": 0.0004}, {"name": "Animal", "id": "01-05_Animal", "percent": 0.042}, {"name": "Ores and Metals", "id": "OresMtls", "percent": 0.0003}, {"name": "Textiles and Clothing", "id": "50-63_TextCloth", "percent": 0.0219}, {"name": "All Products", "id": "Total", "percent": 100}, {"name": "Plastic or Rubber", "id": "39-40_PlastiRub", "percent": 0.3633}, {"name": "Textiles", "id": "Textiles", "percent": 0.0219}, {"name": "Mach and Elec", "id": "84-85_MachElec", "percent": 2.9691}, {"name": "Agricultural Raw Materials", "id": "AgrRaw", "percent": 0.1485}, {"name": "Metals", "id": "72-83_Metals", "percent": 0.31}, {"name": "Fuels", "id": "27-27_Fuels", "percent": 0.0053}, {"name": "Machinery and Transport Equipment", "id": "Transp", "percent": 4.2295}, {"name": "Fuel", "id": "Fuels", "percent": 0.0053}, {"name": "Raw materials", "id": "UNCTAD-SoP1", "percent": 94.0927}, {"name": "Transportation", "id": "86-89_Transport", "percent": 1.2603}, {"name": "Vegetable", "id": "06-15_Vegetable", "percent": 1.5935}, {"name": "Capital goods", "id": "UNCTAD-SoP4", "percent": 3.6575}, {"name": "Stone and Glass", "id": "68-71_StoneGlas", "percent": 0.0026}, {"name": "Consumer goods", "id": "UNCTAD-SoP3", "percent": 2.038}, {"name": "Food", "id": "Food", "percent": 94.9155}, {"name": "Chemical", "id": "Chemical", "percent": 0.0015}, {"name": "Intermediate goods", "id": "UNCTAD-SoP2", "percent": 0.2117}, {"name": "Wood", "id": "44-49_Wood", "percent": 0.021}]}, {"year": 2004, "imports": [{"name": "Manufactures", "id": "manuf", "percent": 44.9009}, {"name": "Food Products", "id": "16-24_FoodProd", "percent": 17.7725}, {"name": "Miscellaneous", "id": "90-99_Miscellan", "percent": 2.1914}, {"name": "Chemicals", "id": "28-38_Chemicals", "percent": 5.5157}, {"name": "Animal", "id": "01-05_Animal", "percent": 5.1424}, {"name": "Ores and Metals", "id": "OresMtls", "percent": 0.408}, {"name": "Footwear", "id": "64-67_Footwear", "percent": 0.4743}, {"name": "Textiles and Clothing", "id": "50-63_TextCloth", "percent": 2.0152}, {"name": "All Products", "id": "Total", "percent": 100}, {"name": "Plastic or Rubber", "id": "39-40_PlastiRub", "percent": 1.806}, {"name": "Textiles", "id": "Textiles", "percent": 2.0374}, {"name": "Mach and Elec", "id": "84-85_MachElec", "percent": 11.5676}, {"name": "Agricultural Raw Materials", "id": "AgrRaw", "percent": 1.0859}, {"name": "Metals", "id": "72-83_Metals", "percent": 3.2362}, {"name": "Fuels", "id": "27-27_Fuels", "percent": 14.9022}, {"name": "Machinery and Transport Equipment", "id": "Transp", "percent": 22.674}, {"name": "Fuel", "id": "Fuels", "percent": 14.7124}, {"name": "Hides and Skins", "id": "41-43_HidesSkin", "percent": 0.0476}, {"name": "Raw materials", "id": "UNCTAD-SoP1", "percent": 6.55}, {"name": "Transportation", "id": "86-89_Transport", "percent": 11.0516}, {"name": "Vegetable", "id": "06-15_Vegetable", "percent": 15.7826}, {"name": "Minerals", "id": "25-26_Minerals", "percent": 4.8719}, {"name": "Capital goods", "id": "UNCTAD-SoP4", "percent": 15.4284}, {"name": "Stone and Glass", "id": "68-71_StoneGlas", "percent": 2.1428}, {"name": "Consumer goods", "id": "UNCTAD-SoP3", "percent": 56.7484}, {"name": "Food", "id": "Food", "percent": 38.664}, {"name": "Chemical", "id": "Chemical", "percent": 5.3565}, {"name": "Intermediate goods", "id": "UNCTAD-SoP2", "percent": 21.0669}, {"name": "Wood", "id": "44-49_Wood", "percent": 1.4801}], "exports": [{"name": "Manufactures", "id": "manuf", "percent": 5.2725}, {"name": "Food Products", "id": "16-24_FoodProd", "percent": 90.5289}, {"name": "Miscellaneous", "id": "90-99_Miscellan", "percent": 0}, {"name": "Chemicals", "id": "28-38_Chemicals", "percent": 0.0068}, {"name": "Animal", "id": "01-05_Animal", "percent": 0.0733}, {"name": "Ores and Metals", "id": "OresMtls", "percent": 0.0896}, {"name": "Textiles and Clothing", "id": "50-63_TextCloth", "percent": 0.0508}, {"name": "All Products", "id": "Total", "percent": 100}, {"name": "Plastic or Rubber", "id": "39-40_PlastiRub", "percent": 0.4464}, {"name": "Textiles", "id": "Textiles", "percent": 0.0508}, {"name": "Mach and Elec", "id": "84-85_MachElec", "percent": 0.5223}, {"name": "Agricultural Raw Materials", "id": "AgrRaw", "percent": 0.3143}, {"name": "Metals", "id": "72-83_Metals", "percent": 3.1956}, {"name": "Machinery and Transport Equipment", "id": "Transp", "percent": 1.5323}, {"name": "Raw materials", "id": "UNCTAD-SoP1", "percent": 92.457}, {"name": "Transportation", "id": "86-89_Transport", "percent": 1.0101}, {"name": "Vegetable", "id": "06-15_Vegetable", "percent": 3.985}, {"name": "Capital goods", "id": "UNCTAD-SoP4", "percent": 0.6462}, {"name": "Consumer goods", "id": "UNCTAD-SoP3", "percent": 6.747}, {"name": "Food", "id": "Food", "percent": 94.3216}, {"name": "Chemical", "id": "Chemical", "percent": 0.3292}, {"name": "Intermediate goods", "id": "UNCTAD-SoP2", "percent": 0.1498}, {"name": "Wood", "id": "44-49_Wood", "percent": 0.1809}]}, {"year": 2005, "imports": [{"name": "Manufactures", "id": "manuf", "percent": 40.1037}, {"name": "Food Products", "id": "16-24_FoodProd", "percent": 16.9904}, {"name": "Miscellaneous", "id": "90-99_Miscellan", "percent": 1.8165}, {"name": "Chemicals", "id": "28-38_Chemicals", "percent": 4.3458}, {"name": "Animal", "id": "01-05_Animal", "percent": 2.9863}, {"name": "Ores and Metals", "id": "OresMtls", "percent": 0.249}, {"name": "Footwear", "id": "64-67_Footwear", "percent": 0.2897}, {"name": "Textiles and Clothing", "id": "50-63_TextCloth", "percent": 1.3212}, {"name": "All Products", "id": "Total", "percent": 100}, {"name": "Plastic or Rubber", "id": "39-40_PlastiRub", "percent": 1.7996}, {"name": "Textiles", "id": "Textiles", "percent": 1.3695}, {"name": "Mach and Elec", "id": "84-85_MachElec", "percent": 8.1445}, {"name": "Agricultural Raw Materials", "id": "AgrRaw", "percent": 0.8649}, {"name": "Metals", "id": "72-83_Metals", "percent": 3.6226}, {"name": "Fuels", "id": "27-27_Fuels", "percent": 20.2453}, {"name": "Machinery and Transport Equipment", "id": "Transp", "percent": 21.2788}, {"name": "Fuel", "id": "Fuels", "percent": 20.2402}, {"name": "Hides and Skins", "id": "41-43_HidesSkin", "percent": 0.0346}, {"name": "Raw materials", "id": "UNCTAD-SoP1", "percent": 9.2616}, {"name": "Transportation", "id": "86-89_Transport", "percent": 13.2308}, {"name": "Vegetable", "id": "06-15_Vegetable", "percent": 18.5401}, {"name": "Minerals", "id": "25-26_Minerals", "percent": 2.9921}, {"name": "Capital goods", "id": "UNCTAD-SoP4", "percent": 11.7539}, {"name": "Stone and Glass", "id": "68-71_StoneGlas", "percent": 2.619}, {"name": "Consumer goods", "id": "UNCTAD-SoP3", "percent": 62.9693}, {"name": "Food", "id": "Food", "percent": 38.4027}, {"name": "Chemical", "id": "Chemical", "percent": 4.2672}, {"name": "Intermediate goods", "id": "UNCTAD-SoP2", "percent": 15.9438}, {"name": "Wood", "id": "44-49_Wood", "percent": 1.0214}], "exports": [{"name": "Manufactures", "id": "manuf", "percent": 4.5118}, {"name": "Food Products", "id": "16-24_FoodProd", "percent": 89.5217}, {"name": "Miscellaneous", "id": "90-99_Miscellan", "percent": 0.1503}, {"name": "Chemicals", "id": "28-38_Chemicals", "percent": 0.0529}, {"name": "Animal", "id": "01-05_Animal", "percent": 0.0423}, {"name": "Ores and Metals", "id": "OresMtls", "percent": 0.0863}, {"name": "Footwear", "id": "64-67_Footwear", "percent": 0.0012}, {"name": "Textiles and Clothing", "id": "50-63_TextCloth", "percent": 0.0356}, {"name": "All Products", "id": "Total", "percent": 100}, {"name": "Plastic or Rubber", "id": "39-40_PlastiRub", "percent": 0.0064}, {"name": "Textiles", "id": "Textiles", "percent": 0.0367}, {"name": "Mach and Elec", "id": "84-85_MachElec", "percent": 1.081}, {"name": "Agricultural Raw Materials", "id": "AgrRaw", "percent": 0.4704}, {"name": "Metals", "id": "72-83_Metals", "percent": 0.5006}, {"name": "Machinery and Transport Equipment", "id": "Transp", "percent": 3.9155}, {"name": "Hides and Skins", "id": "41-43_HidesSkin", "percent": 0.0056}, {"name": "Raw materials", "id": "UNCTAD-SoP1", "percent": 92.2118}, {"name": "Transportation", "id": "86-89_Transport", "percent": 2.8347}, {"name": "Vegetable", "id": "06-15_Vegetable", "percent": 5.7596}, {"name": "Minerals", "id": "25-26_Minerals", "percent": 0.0008}, {"name": "Capital goods", "id": "UNCTAD-SoP4", "percent": 1.4105}, {"name": "Stone and Glass", "id": "68-71_StoneGlas", "percent": 0.0042}, {"name": "Consumer goods", "id": "UNCTAD-SoP3", "percent": 5.8903}, {"name": "Food", "id": "Food", "percent": 94.8675}, {"name": "Chemical", "id": "Chemical", "percent": 0.0529}, {"name": "Intermediate goods", "id": "UNCTAD-SoP2", "percent": 0.4235}, {"name": "Wood", "id": "44-49_Wood", "percent": 0.0032}]}, {"year": 2006, "imports": [{"name": "Manufactures", "id": "manuf", "percent": 46.9305}, {"name": "Food Products", "id": "16-24_FoodProd", "percent": 16.9535}, {"name": "Miscellaneous", "id": "90-99_Miscellan", "percent": 2.8978}, {"name": "Chemicals", "id": "28-38_Chemicals", "percent": 4.074}, {"name": "Animal", "id": "01-05_Animal", "percent": 2.7139}, {"name": "Ores and Metals", "id": "OresMtls", "percent": 1.3625}, {"name": "Footwear", "id": "64-67_Footwear", "percent": 0.9959}, {"name": "Textiles and Clothing", "id": "50-63_TextCloth", "percent": 2.813}, {"name": "All Products", "id": "Total", "percent": 100}, {"name": "Plastic or Rubber", "id": "39-40_PlastiRub", "percent": 3.0264}, {"name": "Textiles", "id": "Textiles", "percent": 3.0286}, {"name": "Mach and Elec", "id": "84-85_MachElec", "percent": 10.9724}, {"name": "Agricultural Raw Materials", "id": "AgrRaw", "percent": 0.7822}, {"name": "Metals", "id": "72-83_Metals", "percent": 6.1932}, {"name": "Fuels", "id": "27-27_Fuels", "percent": 20.2577}, {"name": "Machinery and Transport Equipment", "id": "Transp", "percent": 20.1058}, {"name": "Fuel", "id": "Fuels", "percent": 20.1664}, {"name": "Hides and Skins", "id": "41-43_HidesSkin", "percent": 0.1238}, {"name": "Raw materials", "id": "UNCTAD-SoP1", "percent": 4.3659}, {"name": "Transportation", "id": "86-89_Transport", "percent": 9.1899}, {"name": "Vegetable", "id": "06-15_Vegetable", "percent": 11.1406}, {"name": "Minerals", "id": "25-26_Minerals", "percent": 3.9667}, {"name": "Capital goods", "id": "UNCTAD-SoP4", "percent": 13.1793}, {"name": "Stone and Glass", "id": "68-71_StoneGlas", "percent": 2.5832}, {"name": "Consumer goods", "id": "UNCTAD-SoP3", "percent": 63.5567}, {"name": "Food", "id": "Food", "percent": 30.6046}, {"name": "Chemical", "id": "Chemical", "percent": 4.1254}, {"name": "Intermediate goods", "id": "UNCTAD-SoP2", "percent": 18.7765}, {"name": "Wood", "id": "44-49_Wood", "percent": 2.0978}], "exports": [{"name": "Manufactures", "id": "manuf", "percent": 4.9052}, {"name": "Food Products", "id": "16-24_FoodProd", "percent": 92.6493}, {"name": "Miscellaneous", "id": "90-99_Miscellan", "percent": 0.0264}, {"name": "Animal", "id": "01-05_Animal", "percent": 0.4731}, {"name": "Textiles and Clothing", "id": "50-63_TextCloth", "percent": 0.0583}, {"name": "All Products", "id": "Total", "percent": 100}, {"name": "Plastic or Rubber", "id": "39-40_PlastiRub", "percent": 0.0208}, {"name": "Textiles", "id": "Textiles", "percent": 0.0583}, {"name": "Mach and Elec", "id": "84-85_MachElec", "percent": 0.2066}, {"name": "Agricultural Raw Materials", "id": "AgrRaw", "percent": 0.5625}, {"name": "Metals", "id": "72-83_Metals", "percent": 0.3528}, {"name": "Machinery and Transport Equipment", "id": "Transp", "percent": 3.6755}, {"name": "Raw materials", "id": "UNCTAD-SoP1", "percent": 89.1052}, {"name": "Transportation", "id": "86-89_Transport", "percent": 3.5037}, {"name": "Vegetable", "id": "06-15_Vegetable", "percent": 1.9269}, {"name": "Capital goods", "id": "UNCTAD-SoP4", "percent": 3.3249}, {"name": "Stone and Glass", "id": "68-71_StoneGlas", "percent": 0.1469}, {"name": "Consumer goods", "id": "UNCTAD-SoP3", "percent": 7.4378}, {"name": "Food", "id": "Food", "percent": 94.5296}, {"name": "Intermediate goods", "id": "UNCTAD-SoP2", "percent": 0.132}, {"name": "Wood", "id": "44-49_Wood", "percent": 0.6351}]}, {"year": 2007, "imports": [{"name": "Manufactures", "id": "manuf", "percent": 49.572}, {"name": "Food Products", "id": "16-24_FoodProd", "percent": 14.5543}, {"name": "Miscellaneous", "id": "90-99_Miscellan", "percent": 3.1817}, {"name": "Chemicals", "id": "28-38_Chemicals", "percent": 3.634}, {"name": "Animal", "id": "01-05_Animal", "percent": 1.5648}, {"name": "Ores and Metals", "id": "OresMtls", "percent": 0.9814}, {"name": "Footwear", "id": "64-67_Footwear", "percent": 0.5549}, {"name": "Textiles and Clothing", "id": "50-63_TextCloth", "percent": 1.8166}, {"name": "All Products", "id": "Total", "percent": 100}, {"name": "Plastic or Rubber", "id": "39-40_PlastiRub", "percent": 2.7224}, {"name": "Textiles", "id": "Textiles", "percent": 1.9054}, {"name": "Mach and Elec", "id": "84-85_MachElec", "percent": 14.7771}, {"name": "Agricultural Raw Materials", "id": "AgrRaw", "percent": 0.5096}, {"name": "Metals", "id": "72-83_Metals", "percent": 7.2278}, {"name": "Fuels", "id": "27-27_Fuels", "percent": 20.4586}, {"name": "Machinery and Transport Equipment", "id": "Transp", "percent": 22.9223}, {"name": "Fuel", "id": "Fuels", "percent": 20.2916}, {"name": "Hides and Skins", "id": "41-43_HidesSkin", "percent": 0.0768}, {"name": "Raw materials", "id": "UNCTAD-SoP1", "percent": 4.3757}, {"name": "Transportation", "id": "86-89_Transport", "percent": 7.9527}, {"name": "Vegetable", "id": "06-15_Vegetable", "percent": 12.3154}, {"name": "Minerals", "id": "25-26_Minerals", "percent": 4.3503}, {"name": "Capital goods", "id": "UNCTAD-SoP4", "percent": 16.8732}, {"name": "Stone and Glass", "id": "68-71_StoneGlas", "percent": 3.0558}, {"name": "Consumer goods", "id": "UNCTAD-SoP3", "percent": 59.0735}, {"name": "Food", "id": "Food", "percent": 28.3188}, {"name": "Chemical", "id": "Chemical", "percent": 3.7401}, {"name": "Intermediate goods", "id": "UNCTAD-SoP2", "percent": 19.3678}, {"name": "Wood", "id": "44-49_Wood", "percent": 1.7568}], "exports": [{"name": "Manufactures", "id": "manuf", "percent": 10.5699}, {"name": "Food Products", "id": "16-24_FoodProd", "percent": 53.4791}, {"name": "Miscellaneous", "id": "90-99_Miscellan", "percent": 0.0705}, {"name": "Animal", "id": "01-05_Animal", "percent": 0.4882}, {"name": "Ores and Metals", "id": "OresMtls", "percent": 0.0115}, {"name": "Textiles and Clothing", "id": "50-63_TextCloth", "percent": 0.21}, {"name": "All Products", "id": "Total", "percent": 100}, {"name": "Plastic or Rubber", "id": "39-40_PlastiRub", "percent": 0.2111}, {"name": "Textiles", "id": "Textiles", "percent": 0.21}, {"name": "Mach and Elec", "id": "84-85_MachElec", "percent": 7.4071}, {"name": "Agricultural Raw Materials", "id": "AgrRaw", "percent": 0.6582}, {"name": "Metals", "id": "72-83_Metals", "percent": 0.3736}, {"name": "Fuels", "id": "27-27_Fuels", "percent": 33.3464}, {"name": "Machinery and Transport Equipment", "id": "Transp", "percent": 5.5282}, {"name": "Fuel", "id": "Fuels", "percent": 33.3464}, {"name": "Raw materials", "id": "UNCTAD-SoP1", "percent": 53.2205}, {"name": "Transportation", "id": "86-89_Transport", "percent": 2.4532}, {"name": "Vegetable", "id": "06-15_Vegetable", "percent": 1.8955}, {"name": "Capital goods", "id": "UNCTAD-SoP4", "percent": 8.3671}, {"name": "Stone and Glass", "id": "68-71_StoneGlas", "percent": 0.0527}, {"name": "Consumer goods", "id": "UNCTAD-SoP3", "percent": 38.251}, {"name": "Food", "id": "Food", "percent": 55.4139}, {"name": "Chemical", "id": "Chemical", "percent": 0.0055}, {"name": "Intermediate goods", "id": "UNCTAD-SoP2", "percent": 0.1613}, {"name": "Wood", "id": "44-49_Wood", "percent": 0.0127}]}, {"year": 2008, "imports": [{"name": "Manufactures", "id": "manuf", "percent": 47.9837}, {"name": "Food Products", "id": "16-24_FoodProd", "percent": 11.843}, {"name": "Miscellaneous", "id": "90-99_Miscellan", "percent": 5.1988}, {"name": "Chemicals", "id": "28-38_Chemicals", "percent": 4.0573}, {"name": "Animal", "id": "01-05_Animal", "percent": 2.3495}, {"name": "Ores and Metals", "id": "OresMtls", "percent": 0.9029}, {"name": "Footwear", "id": "64-67_Footwear", "percent": 0.4411}, {"name": "Textiles and Clothing", "id": "50-63_TextCloth", "percent": 2.2264}, {"name": "All Products", "id": "Total", "percent": 100}, {"name": "Plastic or Rubber", "id": "39-40_PlastiRub", "percent": 2.5438}, {"name": "Textiles", "id": "Textiles", "percent": 2.3198}, {"name": "Mach and Elec", "id": "84-85_MachElec", "percent": 13.584}, {"name": "Agricultural Raw Materials", "id": "AgrRaw", "percent": 0.4638}, {"name": "Metals", "id": "72-83_Metals", "percent": 5.1988}, {"name": "Fuels", "id": "27-27_Fuels", "percent": 23.3007}, {"name": "Machinery and Transport Equipment", "id": "Transp", "percent": 21.7311}, {"name": "Fuel", "id": "Fuels", "percent": 23.1327}, {"name": "Hides and Skins", "id": "41-43_HidesSkin", "percent": 0.1213}, {"name": "Raw materials", "id": "UNCTAD-SoP1", "percent": 5.4572}, {"name": "Transportation", "id": "86-89_Transport", "percent": 8.3599}, {"name": "Vegetable", "id": "06-15_Vegetable", "percent": 13.1995}, {"name": "Minerals", "id": "25-26_Minerals", "percent": 3.5483}, {"name": "Capital goods", "id": "UNCTAD-SoP4", "percent": 15.1303}, {"name": "Stone and Glass", "id": "68-71_StoneGlas", "percent": 2.5686}, {"name": "Consumer goods", "id": "UNCTAD-SoP3", "percent": 64.568}, {"name": "Food", "id": "Food", "percent": 27.3086}, {"name": "Chemical", "id": "Chemical", "percent": 4.1668}, {"name": "Intermediate goods", "id": "UNCTAD-SoP2", "percent": 14.6661}, {"name": "Wood", "id": "44-49_Wood", "percent": 1.4591}], "exports": [{"name": "Manufactures", "id": "manuf", "percent": 4.1701}, {"name": "Food Products", "id": "16-24_FoodProd", "percent": 48.4013}, {"name": "Miscellaneous", "id": "90-99_Miscellan", "percent": 0.0714}, {"name": "Chemicals", "id": "28-38_Chemicals", "percent": 0.2799}, {"name": "Animal", "id": "01-05_Animal", "percent": 0.1246}, {"name": "Ores and Metals", "id": "OresMtls", "percent": 0.009}, {"name": "Textiles and Clothing", "id": "50-63_TextCloth", "percent": 0.0399}, {"name": "All Products", "id": "Total", "percent": 100}, {"name": "Plastic or Rubber", "id": "39-40_PlastiRub", "percent": 0.2034}, {"name": "Textiles", "id": "Textiles", "percent": 0.0399}, {"name": "Mach and Elec", "id": "84-85_MachElec", "percent": 1.3417}, {"name": "Agricultural Raw Materials", "id": "AgrRaw", "percent": 0.2715}, {"name": "Metals", "id": "72-83_Metals", "percent": 0.5849}, {"name": "Fuels", "id": "27-27_Fuels", "percent": 46.5152}, {"name": "Machinery and Transport Equipment", "id": "Transp", "percent": 2.9489}, {"name": "Fuel", "id": "Fuels", "percent": 46.5152}, {"name": "Raw materials", "id": "UNCTAD-SoP1", "percent": 47.8981}, {"name": "Transportation", "id": "86-89_Transport", "percent": 1.6072}, {"name": "Vegetable", "id": "06-15_Vegetable", "percent": 0.7765}, {"name": "Capital goods", "id": "UNCTAD-SoP4", "percent": 1.3205}, {"name": "Stone and Glass", "id": "68-71_StoneGlas", "percent": 0.0366}, {"name": "Consumer goods", "id": "UNCTAD-SoP3", "percent": 50.7009}, {"name": "Food", "id": "Food", "percent": 49.0314}, {"name": "Chemical", "id": "Chemical", "percent": 0.2688}, {"name": "Intermediate goods", "id": "UNCTAD-SoP2", "percent": 0.0805}, {"name": "Wood", "id": "44-49_Wood", "percent": 0.0175}]}, {"year": 2009, "imports": [{"name": "Manufactures", "id": "manuf", "percent": 46.5652}, {"name": "Food Products", "id": "16-24_FoodProd", "percent": 14.7091}, {"name": "Miscellaneous", "id": "90-99_Miscellan", "percent": 3.0237}, {"name": "Chemicals", "id": "28-38_Chemicals", "percent": 5.4918}, {"name": "Animal", "id": "01-05_Animal", "percent": 5.7665}, {"name": "Ores and Metals", "id": "OresMtls", "percent": 1.0775}, {"name": "Footwear", "id": "64-67_Footwear", "percent": 0.5574}, {"name": "Textiles and Clothing", "id": "50-63_TextCloth", "percent": 1.5553}, {"name": "All Products", "id": "Total", "percent": 100}, {"name": "Plastic or Rubber", "id": "39-40_PlastiRub", "percent": 2.6271}, {"name": "Textiles", "id": "Textiles", "percent": 1.6435}, {"name": "Mach and Elec", "id": "84-85_MachElec", "percent": 11.8676}, {"name": "Agricultural Raw Materials", "id": "AgrRaw", "percent": 0.8557}, {"name": "Metals", "id": "72-83_Metals", "percent": 5.4169}, {"name": "Fuels", "id": "27-27_Fuels", "percent": 15.5222}, {"name": "Machinery and Transport Equipment", "id": "Transp", "percent": 22.6173}, {"name": "Fuel", "id": "Fuels", "percent": 15.4218}, {"name": "Hides and Skins", "id": "41-43_HidesSkin", "percent": 0.082}, {"name": "Raw materials", "id": "UNCTAD-SoP1", "percent": 8.553}, {"name": "Transportation", "id": "86-89_Transport", "percent": 10.5188}, {"name": "Vegetable", "id": "06-15_Vegetable", "percent": 15.7661}, {"name": "Minerals", "id": "25-26_Minerals", "percent": 3.3873}, {"name": "Capital goods", "id": "UNCTAD-SoP4", "percent": 14.2125}, {"name": "Stone and Glass", "id": "68-71_StoneGlas", "percent": 2.3282}, {"name": "Consumer goods", "id": "UNCTAD-SoP3", "percent": 59.3249}, {"name": "Food", "id": "Food", "percent": 35.9074}, {"name": "Chemical", "id": "Chemical", "percent": 5.5735}, {"name": "Intermediate goods", "id": "UNCTAD-SoP2", "percent": 17.7396}, {"name": "Wood", "id": "44-49_Wood", "percent": 1.3801}], "exports": [{"name": "Manufactures", "id": "manuf", "percent": 2.5626}, {"name": "Food Products", "id": "16-24_FoodProd", "percent": 69.5091}, {"name": "Miscellaneous", "id": "90-99_Miscellan", "percent": 3.3377}, {"name": "Animal", "id": "01-05_Animal", "percent": 0.1712}, {"name": "Ores and Metals", "id": "OresMtls", "percent": 0.0167}, {"name": "Footwear", "id": "64-67_Footwear", "percent": 0.0059}, {"name": "Textiles and Clothing", "id": "50-63_TextCloth", "percent": 0.3634}, {"name": "All Products", "id": "Total", "percent": 100}, {"name": "Plastic or Rubber", "id": "39-40_PlastiRub", "percent": 0.0805}, {"name": "Textiles", "id": "Textiles", "percent": 0.363}, {"name": "Mach and Elec", "id": "84-85_MachElec", "percent": 0.6671}, {"name": "Agricultural Raw Materials", "id": "AgrRaw", "percent": 0.5138}, {"name": "Metals", "id": "72-83_Metals", "percent": 0.295}, {"name": "Fuels", "id": "27-27_Fuels", "percent": 22.7999}, {"name": "Machinery and Transport Equipment", "id": "Transp", "percent": 1.3861}, {"name": "Fuel", "id": "Fuels", "percent": 22.7999}, {"name": "Raw materials", "id": "UNCTAD-SoP1", "percent": 69.1269}, {"name": "Transportation", "id": "86-89_Transport", "percent": 0.719}, {"name": "Vegetable", "id": "06-15_Vegetable", "percent": 1.9366}, {"name": "Capital goods", "id": "UNCTAD-SoP4", "percent": 0.991}, {"name": "Consumer goods", "id": "UNCTAD-SoP3", "percent": 26.5819}, {"name": "Food", "id": "Food", "percent": 71.142}, {"name": "Chemical", "id": "Chemical", "percent": 0.0019}, {"name": "Intermediate goods", "id": "UNCTAD-SoP2", "percent": 0.3613}, {"name": "Wood", "id": "44-49_Wood", "percent": 0.1147}]}, {"year": 2010, "imports": [{"name": "Manufactures", "id": "manuf", "percent": 51.9654}, {"name": "Food Products", "id": "16-24_FoodProd", "percent": 14.2976}, {"name": "Miscellaneous", "id": "90-99_Miscellan", "percent": 3.4956}, {"name": "Chemicals", "id": "28-38_Chemicals", "percent": 4.7285}, {"name": "Animal", "id": "01-05_Animal", "percent": 3.0755}, {"name": "Ores and Metals", "id": "OresMtls", "percent": 1.0846}, {"name": "Footwear", "id": "64-67_Footwear", "percent": 1.2209}, {"name": "Textiles and Clothing", "id": "50-63_TextCloth", "percent": 2.4455}, {"name": "All Products", "id": "Total", "percent": 100}, {"name": "Plastic or Rubber", "id": "39-40_PlastiRub", "percent": 2.6137}, {"name": "Textiles", "id": "Textiles", "percent": 2.9135}, {"name": "Mach and Elec", "id": "84-85_MachElec", "percent": 13.7578}, {"name": "Agricultural Raw Materials", "id": "AgrRaw", "percent": 0.7748}, {"name": "Metals", "id": "72-83_Metals", "percent": 4.4612}, {"name": "Fuels", "id": "27-27_Fuels", "percent": 16.197}, {"name": "Machinery and Transport Equipment", "id": "Transp", "percent": 27.091}, {"name": "Fuel", "id": "Fuels", "percent": 16.0984}, {"name": "Hides and Skins", "id": "41-43_HidesSkin", "percent": 0.2871}, {"name": "Raw materials", "id": "UNCTAD-SoP1", "percent": 7.4319}, {"name": "Transportation", "id": "86-89_Transport", "percent": 13.4832}, {"name": "Vegetable", "id": "06-15_Vegetable", "percent": 12.542}, {"name": "Minerals", "id": "25-26_Minerals", "percent": 4.0037}, {"name": "Capital goods", "id": "UNCTAD-SoP4", "percent": 17.8452}, {"name": "Stone and Glass", "id": "68-71_StoneGlas", "percent": 1.677}, {"name": "Consumer goods", "id": "UNCTAD-SoP3", "percent": 58.1119}, {"name": "Food", "id": "Food", "percent": 29.8266}, {"name": "Chemical", "id": "Chemical", "percent": 4.615}, {"name": "Intermediate goods", "id": "UNCTAD-SoP2", "percent": 16.3812}, {"name": "Wood", "id": "44-49_Wood", "percent": 1.7135}], "exports": [{"name": "Manufactures", "id": "manuf", "percent": 4.6644}, {"name": "Food Products", "id": "16-24_FoodProd", "percent": 88.8071}, {"name": "Miscellaneous", "id": "90-99_Miscellan", "percent": 0.6683}, {"name": "Animal", "id": "01-05_Animal", "percent": 0.1632}, {"name": "Ores and Metals", "id": "OresMtls", "percent": 0.0146}, {"name": "Footwear", "id": "64-67_Footwear", "percent": 0.0013}, {"name": "Textiles and Clothing", "id": "50-63_TextCloth", "percent": 0.213}, {"name": "All Products", "id": "Total", "percent": 100}, {"name": "Plastic or Rubber", "id": "39-40_PlastiRub", "percent": 0.2052}, {"name": "Textiles", "id": "Textiles", "percent": 0.2134}, {"name": "Mach and Elec", "id": "84-85_MachElec", "percent": 1.8009}, {"name": "Agricultural Raw Materials", "id": "AgrRaw", "percent": 0.6701}, {"name": "Metals", "id": "72-83_Metals", "percent": 0.1411}, {"name": "Machinery and Transport Equipment", "id": "Transp", "percent": 3.2719}, {"name": "Hides and Skins", "id": "41-43_HidesSkin", "percent": 0.0082}, {"name": "Raw materials", "id": "UNCTAD-SoP1", "percent": 86.2716}, {"name": "Transportation", "id": "86-89_Transport", "percent": 1.4711}, {"name": "Vegetable", "id": "06-15_Vegetable", "percent": 6.1139}, {"name": "Capital goods", "id": "UNCTAD-SoP4", "percent": 1.4698}, {"name": "Stone and Glass", "id": "68-71_StoneGlas", "percent": 0.3571}, {"name": "Consumer goods", "id": "UNCTAD-SoP3", "percent": 8.2317}, {"name": "Food", "id": "Food", "percent": 94.6162}, {"name": "Intermediate goods", "id": "UNCTAD-SoP2", "percent": 3.9922}, {"name": "Wood", "id": "44-49_Wood", "percent": 0.0497}]}, {"year": 2011, "imports": [{"name": "Manufactures", "id": "manuf", "percent": 48.8533}, {"name": "Food Products", "id": "16-24_FoodProd", "percent": 14.7853}, {"name": "Miscellaneous", "id": "90-99_Miscellan", "percent": 3.0699}, {"name": "Chemicals", "id": "28-38_Chemicals", "percent": 4.3504}, {"name": "Animal", "id": "01-05_Animal", "percent": 3.8947}, {"name": "Ores and Metals", "id": "OresMtls", "percent": 1.7581}, {"name": "Footwear", "id": "64-67_Footwear", "percent": 0.8405}, {"name": "Textiles and Clothing", "id": "50-63_TextCloth", "percent": 2.3823}, {"name": "All Products", "id": "Total", "percent": 100}, {"name": "Plastic or Rubber", "id": "39-40_PlastiRub", "percent": 3.0602}, {"name": "Textiles", "id": "Textiles", "percent": 2.7309}, {"name": "Mach and Elec", "id": "84-85_MachElec", "percent": 14.5686}, {"name": "Agricultural Raw Materials", "id": "AgrRaw", "percent": 0.8333}, {"name": "Metals", "id": "72-83_Metals", "percent": 4.3188}, {"name": "Fuels", "id": "27-27_Fuels", "percent": 16.6081}, {"name": "Machinery and Transport Equipment", "id": "Transp", "percent": 24.1575}, {"name": "Fuel", "id": "Fuels", "percent": 15.9699}, {"name": "Hides and Skins", "id": "41-43_HidesSkin", "percent": 0.1138}, {"name": "Raw materials", "id": "UNCTAD-SoP1", "percent": 8.9219}, {"name": "Transportation", "id": "86-89_Transport", "percent": 9.783}, {"name": "Vegetable", "id": "06-15_Vegetable", "percent": 13.8867}, {"name": "Minerals", "id": "25-26_Minerals", "percent": 3.3552}, {"name": "Capital goods", "id": "UNCTAD-SoP4", "percent": 19.1011}, {"name": "Stone and Glass", "id": "68-71_StoneGlas", "percent": 1.4919}, {"name": "Consumer goods", "id": "UNCTAD-SoP3", "percent": 54.6813}, {"name": "Food", "id": "Food", "percent": 32.4124}, {"name": "Chemical", "id": "Chemical", "percent": 4.5107}, {"name": "Intermediate goods", "id": "UNCTAD-SoP2", "percent": 17.1377}, {"name": "Wood", "id": "44-49_Wood", "percent": 3.4906}], "exports": [{"name": "Manufactures", "id": "manuf", "percent": 2.4663}, {"name": "Food Products", "id": "16-24_FoodProd", "percent": 49.1918}, {"name": "Miscellaneous", "id": "90-99_Miscellan", "percent": 0.3567}, {"name": "Chemicals", "id": "28-38_Chemicals", "percent": 0.0306}, {"name": "Animal", "id": "01-05_Animal", "percent": 0.2692}, {"name": "Ores and Metals", "id": "OresMtls", "percent": 0.0948}, {"name": "Footwear", "id": "64-67_Footwear", "percent": 0.0701}, {"name": "Textiles and Clothing", "id": "50-63_TextCloth", "percent": 0.2994}, {"name": "All Products", "id": "Total", "percent": 100}, {"name": "Plastic or Rubber", "id": "39-40_PlastiRub", "percent": 0.1272}, {"name": "Textiles", "id": "Textiles", "percent": 0.3694}, {"name": "Mach and Elec", "id": "84-85_MachElec", "percent": 0.3517}, {"name": "Agricultural Raw Materials", "id": "AgrRaw", "percent": 0.0711}, {"name": "Metals", "id": "72-83_Metals", "percent": 0.3172}, {"name": "Fuels", "id": "27-27_Fuels", "percent": 46.1659}, {"name": "Machinery and Transport Equipment", "id": "Transp", "percent": 1.1368}, {"name": "Fuel", "id": "Fuels", "percent": 46.1659}, {"name": "Hides and Skins", "id": "41-43_HidesSkin", "percent": 0.2647}, {"name": "Raw materials", "id": "UNCTAD-SoP1", "percent": 48.6056}, {"name": "Transportation", "id": "86-89_Transport", "percent": 0.7857}, {"name": "Vegetable", "id": "06-15_Vegetable", "percent": 1.7217}, {"name": "Capital goods", "id": "UNCTAD-SoP4", "percent": 0.5522}, {"name": "Stone and Glass", "id": "68-71_StoneGlas", "percent": 0.0203}, {"name": "Consumer goods", "id": "UNCTAD-SoP3", "percent": 50.6092}, {"name": "Food", "id": "Food", "percent": 51.1531}, {"name": "Chemical", "id": "Chemical", "percent": 0.0306}, {"name": "Intermediate goods", "id": "UNCTAD-SoP2", "percent": 0.1842}, {"name": "Wood", "id": "44-49_Wood", "percent": 0.028}]}, {"year": 2012, "imports": [{"name": "Manufactures", "id": "manuf", "percent": 42.1877}, {"name": "Food Products", "id": "16-24_FoodProd", "percent": 13.875}, {"name": "Miscellaneous", "id": "90-99_Miscellan", "percent": 3.0084}, {"name": "Chemicals", "id": "28-38_Chemicals", "percent": 4.7952}, {"name": "Animal", "id": "01-05_Animal", "percent": 3.986}, {"name": "Ores and Metals", "id": "OresMtls", "percent": 0.8944}, {"name": "Footwear", "id": "64-67_Footwear", "percent": 0.4928}, {"name": "Textiles and Clothing", "id": "50-63_TextCloth", "percent": 2.0754}, {"name": "All Products", "id": "Total", "percent": 100}, {"name": "Plastic or Rubber", "id": "39-40_PlastiRub", "percent": 2.707}, {"name": "Textiles", "id": "Textiles", "percent": 2.1835}, {"name": "Mach and Elec", "id": "84-85_MachElec", "percent": 10.8727}, {"name": "Agricultural Raw Materials", "id": "AgrRaw", "percent": 0.7933}, {"name": "Metals", "id": "72-83_Metals", "percent": 4.7478}, {"name": "Fuels", "id": "27-27_Fuels", "percent": 25.8913}, {"name": "Machinery and Transport Equipment", "id": "Transp", "percent": 19.8197}, {"name": "Fuel", "id": "Fuels", "percent": 25.7532}, {"name": "Hides and Skins", "id": "41-43_HidesSkin", "percent": 0.1293}, {"name": "Raw materials", "id": "UNCTAD-SoP1", "percent": 6.037}, {"name": "Transportation", "id": "86-89_Transport", "percent": 9.0716}, {"name": "Vegetable", "id": "06-15_Vegetable", "percent": 12.6179}, {"name": "Minerals", "id": "25-26_Minerals", "percent": 2.6588}, {"name": "Capital goods", "id": "UNCTAD-SoP4", "percent": 14.6763}, {"name": "Stone and Glass", "id": "68-71_StoneGlas", "percent": 1.6695}, {"name": "Consumer goods", "id": "UNCTAD-SoP3", "percent": 63.3086}, {"name": "Food", "id": "Food", "percent": 30.3603}, {"name": "Chemical", "id": "Chemical", "percent": 4.9269}, {"name": "Intermediate goods", "id": "UNCTAD-SoP2", "percent": 15.9722}, {"name": "Wood", "id": "44-49_Wood", "percent": 1.4012}], "exports": [{"name": "Manufactures", "id": "manuf", "percent": 11.5702}, {"name": "Food Products", "id": "16-24_FoodProd", "percent": 83.6626}, {"name": "Miscellaneous", "id": "90-99_Miscellan", "percent": 2.5004}, {"name": "Animal", "id": "01-05_Animal", "percent": 0.0184}, {"name": "Ores and Metals", "id": "OresMtls", "percent": 0.1204}, {"name": "Footwear", "id": "64-67_Footwear", "percent": 0.0042}, {"name": "Textiles and Clothing", "id": "50-63_TextCloth", "percent": 0.2228}, {"name": "All Products", "id": "Total", "percent": 100}, {"name": "Plastic or Rubber", "id": "39-40_PlastiRub", "percent": 0.1971}, {"name": "Textiles", "id": "Textiles", "percent": 0.2228}, {"name": "Mach and Elec", "id": "84-85_MachElec", "percent": 0.849}, {"name": "Agricultural Raw Materials", "id": "AgrRaw", "percent": 0.2762}, {"name": "Metals", "id": "72-83_Metals", "percent": 3.8921}, {"name": "Fuels", "id": "27-27_Fuels", "percent": 0.7464}, {"name": "Machinery and Transport Equipment", "id": "Transp", "percent": 3.2834}, {"name": "Fuel", "id": "Fuels", "percent": 0.7464}, {"name": "Hides and Skins", "id": "41-43_HidesSkin", "percent": 0.0616}, {"name": "Raw materials", "id": "UNCTAD-SoP1", "percent": 81.9672}, {"name": "Transportation", "id": "86-89_Transport", "percent": 2.4858}, {"name": "Vegetable", "id": "06-15_Vegetable", "percent": 3.6392}, {"name": "Capital goods", "id": "UNCTAD-SoP4", "percent": 2.5525}, {"name": "Stone and Glass", "id": "68-71_StoneGlas", "percent": 0.1482}, {"name": "Consumer goods", "id": "UNCTAD-SoP3", "percent": 15.3195}, {"name": "Food", "id": "Food", "percent": 87.2464}, {"name": "Intermediate goods", "id": "UNCTAD-SoP2", "percent": 0.1204}, {"name": "Wood", "id": "44-49_Wood", "percent": 1.5722}]}, {"year": 2013, "imports": [{"name": "Manufactures", "id": "manuf", "percent": 41.017}, {"name": "Food Products", "id": "16-24_FoodProd", "percent": 14.7513}, {"name": "Miscellaneous", "id": "90-99_Miscellan", "percent": 2.7643}, {"name": "Chemicals", "id": "28-38_Chemicals", "percent": 4.9751}, {"name": "Animal", "id": "01-05_Animal", "percent": 4.2971}, {"name": "Ores and Metals", "id": "OresMtls", "percent": 1.2351}, {"name": "Footwear", "id": "64-67_Footwear", "percent": 0.6476}, {"name": "Textiles and Clothing", "id": "50-63_TextCloth", "percent": 1.9497}, {"name": "All Products", "id": "Total", "percent": 100}, {"name": "Plastic or Rubber", "id": "39-40_PlastiRub", "percent": 2.7841}, {"name": "Textiles", "id": "Textiles", "percent": 2.0921}, {"name": "Mach and Elec", "id": "84-85_MachElec", "percent": 12.0412}, {"name": "Agricultural Raw Materials", "id": "AgrRaw", "percent": 0.8665}, {"name": "Metals", "id": "72-83_Metals", "percent": 4.9727}, {"name": "Fuels", "id": "27-27_Fuels", "percent": 26.4964}, {"name": "Machinery and Transport Equipment", "id": "Transp", "percent": 18.2056}, {"name": "Fuel", "id": "Fuels", "percent": 26.2359}, {"name": "Hides and Skins", "id": "41-43_HidesSkin", "percent": 0.1029}, {"name": "Raw materials", "id": "UNCTAD-SoP1", "percent": 4.7965}, {"name": "Transportation", "id": "86-89_Transport", "percent": 6.3795}, {"name": "Vegetable", "id": "06-15_Vegetable", "percent": 11.655}, {"name": "Minerals", "id": "25-26_Minerals", "percent": 2.7701}, {"name": "Capital goods", "id": "UNCTAD-SoP4", "percent": 13.5341}, {"name": "Stone and Glass", "id": "68-71_StoneGlas", "percent": 1.8741}, {"name": "Consumer goods", "id": "UNCTAD-SoP3", "percent": 65.6123}, {"name": "Food", "id": "Food", "percent": 30.632}, {"name": "Chemical", "id": "Chemical", "percent": 4.9497}, {"name": "Intermediate goods", "id": "UNCTAD-SoP2", "percent": 16.0448}, {"name": "Wood", "id": "44-49_Wood", "percent": 1.5389}], "exports": [{"name": "Manufactures", "id": "manuf", "percent": 11.6849}, {"name": "Food Products", "id": "16-24_FoodProd", "percent": 81.3572}, {"name": "Miscellaneous", "id": "90-99_Miscellan", "percent": 1.0269}, {"name": "Chemicals", "id": "28-38_Chemicals", "percent": 0.1909}, {"name": "Animal", "id": "01-05_Animal", "percent": 0.0156}, {"name": "Ores and Metals", "id": "OresMtls", "percent": 1.138}, {"name": "Footwear", "id": "64-67_Footwear", "percent": 0.0226}, {"name": "Textiles and Clothing", "id": "50-63_TextCloth", "percent": 1.9041}, {"name": "All Products", "id": "Total", "percent": 100}, {"name": "Plastic or Rubber", "id": "39-40_PlastiRub", "percent": 0.388}, {"name": "Textiles", "id": "Textiles", "percent": 1.9058}, {"name": "Mach and Elec", "id": "84-85_MachElec", "percent": 6.85}, {"name": "Agricultural Raw Materials", "id": "AgrRaw", "percent": 1.8956}, {"name": "Metals", "id": "72-83_Metals", "percent": 1.7848}, {"name": "Machinery and Transport Equipment", "id": "Transp", "percent": 8.421}, {"name": "Hides and Skins", "id": "41-43_HidesSkin", "percent": 0.0082}, {"name": "Raw materials", "id": "UNCTAD-SoP1", "percent": 81.6605}, {"name": "Transportation", "id": "86-89_Transport", "percent": 1.5879}, {"name": "Vegetable", "id": "06-15_Vegetable", "percent": 3.9556}, {"name": "Capital goods", "id": "UNCTAD-SoP4", "percent": 8.1114}, {"name": "Stone and Glass", "id": "68-71_StoneGlas", "percent": 0.8798}, {"name": "Consumer goods", "id": "UNCTAD-SoP3", "percent": 9.5847}, {"name": "Food", "id": "Food", "percent": 85.2814}, {"name": "Chemical", "id": "Chemical", "percent": 0.1909}, {"name": "Intermediate goods", "id": "UNCTAD-SoP2", "percent": 0.6434}, {"name": "Wood", "id": "44-49_Wood", "percent": 0.0285}]}, {"year": 2014, "imports": [{"name": "Manufactures", "id": "manuf", "percent": 42.8419}, {"name": "Food Products", "id": "16-24_FoodProd", "percent": 15.4206}, {"name": "Miscellaneous", "id": "90-99_Miscellan", "percent": 2.4971}, {"name": "Chemicals", "id": "28-38_Chemicals", "percent": 4.4514}, {"name": "Animal", "id": "01-05_Animal", "percent": 5.6817}, {"name": "Ores and Metals", "id": "OresMtls", "percent": 1.1251}, {"name": "Footwear", "id": "64-67_Footwear", "percent": 0.8845}, {"name": "Textiles and Clothing", "id": "50-63_TextCloth", "percent": 2.9932}, {"name": "All Products", "id": "Total", "percent": 100}, {"name": "Plastic or Rubber", "id": "39-40_PlastiRub", "percent": 2.8316}, {"name": "Textiles", "id": "Textiles", "percent": 3.2884}, {"name": "Mach and Elec", "id": "84-85_MachElec", "percent": 11.3165}, {"name": "Agricultural Raw Materials", "id": "AgrRaw", "percent": 0.8057}, {"name": "Metals", "id": "72-83_Metals", "percent": 5.8892}, {"name": "Fuels", "id": "27-27_Fuels", "percent": 22.8893}, {"name": "Machinery and Transport Equipment", "id": "Transp", "percent": 18.3002}, {"name": "Fuel", "id": "Fuels", "percent": 22.8339}, {"name": "Hides and Skins", "id": "41-43_HidesSkin", "percent": 0.1257}, {"name": "Raw materials", "id": "UNCTAD-SoP1", "percent": 5.8134}, {"name": "Transportation", "id": "86-89_Transport", "percent": 7.2199}, {"name": "Vegetable", "id": "06-15_Vegetable", "percent": 11.327}, {"name": "Minerals", "id": "25-26_Minerals", "percent": 3.6142}, {"name": "Capital goods", "id": "UNCTAD-SoP4", "percent": 13.0343}, {"name": "Stone and Glass", "id": "68-71_StoneGlas", "percent": 1.2719}, {"name": "Consumer goods", "id": "UNCTAD-SoP3", "percent": 64.4157}, {"name": "Food", "id": "Food", "percent": 32.3538}, {"name": "Chemical", "id": "Chemical", "percent": 4.5786}, {"name": "Intermediate goods", "id": "UNCTAD-SoP2", "percent": 16.7113}, {"name": "Wood", "id": "44-49_Wood", "percent": 1.5863}], "exports": [{"name": "Manufactures", "id": "manuf", "percent": 2.8016}, {"name": "Food Products", "id": "16-24_FoodProd", "percent": 91.4401}, {"name": "Miscellaneous", "id": "90-99_Miscellan", "percent": 0.7911}, {"name": "Chemicals", "id": "28-38_Chemicals", "percent": 0.0046}, {"name": "Animal", "id": "01-05_Animal", "percent": 0.1872}, {"name": "Ores and Metals", "id": "OresMtls", "percent": 0.1332}, {"name": "Footwear", "id": "64-67_Footwear", "percent": 0.0032}, {"name": "Textiles and Clothing", "id": "50-63_TextCloth", "percent": 0.0713}, {"name": "All Products", "id": "Total", "percent": 100}, {"name": "Plastic or Rubber", "id": "39-40_PlastiRub", "percent": 0.3072}, {"name": "Textiles", "id": "Textiles", "percent": 0.0718}, {"name": "Mach and Elec", "id": "84-85_MachElec", "percent": 0.6187}, {"name": "Agricultural Raw Materials", "id": "AgrRaw", "percent": 0.0507}, {"name": "Metals", "id": "72-83_Metals", "percent": 0.2473}, {"name": "Machinery and Transport Equipment", "id": "Transp", "percent": 1.398}, {"name": "Hides and Skins", "id": "41-43_HidesSkin", "percent": 0.0044}, {"name": "Raw materials", "id": "UNCTAD-SoP1", "percent": 92.718}, {"name": "Transportation", "id": "86-89_Transport", "percent": 0.7844}, {"name": "Vegetable", "id": "06-15_Vegetable", "percent": 5.4116}, {"name": "Minerals", "id": "25-26_Minerals", "percent": 0.0039}, {"name": "Capital goods", "id": "UNCTAD-SoP4", "percent": 0.7743}, {"name": "Stone and Glass", "id": "68-71_StoneGlas", "percent": 0.0453}, {"name": "Consumer goods", "id": "UNCTAD-SoP3", "percent": 6.2305}, {"name": "Food", "id": "Food", "percent": 97.0122}, {"name": "Chemical", "id": "Chemical", "percent": 0.0046}, {"name": "Intermediate goods", "id": "UNCTAD-SoP2", "percent": 0.2756}, {"name": "Wood", "id": "44-49_Wood", "percent": 0.0798}]}, {"year": 2015, "imports": [{"name": "Manufactures", "id": "manuf", "percent": 44.63}, {"name": "Food Products", "id": "16-24_FoodProd", "percent": 14.0954}, {"name": "Miscellaneous", "id": "90-99_Miscellan", "percent": 25.8181}, {"name": "Chemicals", "id": "28-38_Chemicals", "percent": 3.9389}, {"name": "Animal", "id": "01-05_Animal", "percent": 4.5646}, {"name": "Ores and Metals", "id": "OresMtls", "percent": 1.0575}, {"name": "Footwear", "id": "64-67_Footwear", "percent": 0.716}, {"name": "Textiles and Clothing", "id": "50-63_TextCloth", "percent": 2.1726}, {"name": "All Products", "id": "Total", "percent": 100}, {"name": "Plastic or Rubber", "id": "39-40_PlastiRub", "percent": 3.1739}, {"name": "Textiles", "id": "Textiles", "percent": 2.2959}, {"name": "Mach and Elec", "id": "84-85_MachElec", "percent": 11.5183}, {"name": "Agricultural Raw Materials", "id": "AgrRaw", "percent": 0.6968}, {"name": "Metals", "id": "72-83_Metals", "percent": 4.8177}, {"name": "Fuels", "id": "27-27_Fuels", "percent": 0.5102}, {"name": "Machinery and Transport Equipment", "id": "Transp", "percent": 18.1404}, {"name": "Fuel", "id": "Fuels", "percent": 0.4535}, {"name": "Hides and Skins", "id": "41-43_HidesSkin", "percent": 0.1568}, {"name": "Raw materials", "id": "UNCTAD-SoP1", "percent": 5.8027}, {"name": "Transportation", "id": "86-89_Transport", "percent": 6.9405}, {"name": "Vegetable", "id": "06-15_Vegetable", "percent": 12.449}, {"name": "Minerals", "id": "25-26_Minerals", "percent": 3.2363}, {"name": "Capital goods", "id": "UNCTAD-SoP4", "percent": 14.1655}, {"name": "Stone and Glass", "id": "68-71_StoneGlas", "percent": 4.0808}, {"name": "Consumer goods", "id": "UNCTAD-SoP3", "percent": 43.2671}, {"name": "Food", "id": "Food", "percent": 31.0408}, {"name": "Chemical", "id": "Chemical", "percent": 4.1122}, {"name": "Intermediate goods", "id": "UNCTAD-SoP2", "percent": 14.6561}, {"name": "Wood", "id": "44-49_Wood", "percent": 1.8109}], "exports": [{"name": "Manufactures", "id": "manuf", "percent": 5.1356}, {"name": "Food Products", "id": "16-24_FoodProd", "percent": 89.4186}, {"name": "Miscellaneous", "id": "90-99_Miscellan", "percent": 0.4741}, {"name": "Chemicals", "id": "28-38_Chemicals", "percent": 0.2539}, {"name": "Animal", "id": "01-05_Animal", "percent": 0.5512}, {"name": "Ores and Metals", "id": "OresMtls", "percent": 1.3101}, {"name": "Footwear", "id": "64-67_Footwear", "percent": 0.007}, {"name": "Textiles and Clothing", "id": "50-63_TextCloth", "percent": 0.2777}, {"name": "All Products", "id": "Total", "percent": 100}, {"name": "Plastic or Rubber", "id": "39-40_PlastiRub", "percent": 0.1727}, {"name": "Textiles", "id": "Textiles", "percent": 0.2808}, {"name": "Mach and Elec", "id": "84-85_MachElec", "percent": 3.2096}, {"name": "Agricultural Raw Materials", "id": "AgrRaw", "percent": 0.2975}, {"name": "Metals", "id": "72-83_Metals", "percent": 1.3983}, {"name": "Machinery and Transport Equipment", "id": "Transp", "percent": 3.9573}, {"name": "Hides and Skins", "id": "41-43_HidesSkin", "percent": 0.05}, {"name": "Raw materials", "id": "UNCTAD-SoP1", "percent": 90.1328}, {"name": "Transportation", "id": "86-89_Transport", "percent": 0.7767}, {"name": "Vegetable", "id": "06-15_Vegetable", "percent": 3.3146}, {"name": "Minerals", "id": "25-26_Minerals", "percent": 0.0015}, {"name": "Capital goods", "id": "UNCTAD-SoP4", "percent": 3.236}, {"name": "Stone and Glass", "id": "68-71_StoneGlas", "percent": 0.0164}, {"name": "Consumer goods", "id": "UNCTAD-SoP3", "percent": 6.1362}, {"name": "Food", "id": "Food", "percent": 93.2568}, {"name": "Chemical", "id": "Chemical", "percent": 0.2638}, {"name": "Intermediate goods", "id": "UNCTAD-SoP2", "percent": 0.4951}, {"name": "Wood", "id": "44-49_Wood", "percent": 0.0776}]}, {"year": 2016, "imports": [{"name": "Manufactures", "id": "manuf", "percent": 48.8606}, {"name": "Food Products", "id": "16-24_FoodProd", "percent": 15.6708}, {"name": "Miscellaneous", "id": "90-99_Miscellan", "percent": 18.3247}, {"name": "Chemicals", "id": "28-38_Chemicals", "percent": 4.6516}, {"name": "Animal", "id": "01-05_Animal", "percent": 4.8915}, {"name": "Ores and Metals", "id": "OresMtls", "percent": 1.5288}, {"name": "Footwear", "id": "64-67_Footwear", "percent": 0.8763}, {"name": "Textiles and Clothing", "id": "50-63_TextCloth", "percent": 2.6537}, {"name": "All Products", "id": "Total", "percent": 100}, {"name": "Plastic or Rubber", "id": "39-40_PlastiRub", "percent": 3.4203}, {"name": "Textiles", "id": "Textiles", "percent": 2.8913}, {"name": "Mach and Elec", "id": "84-85_MachElec", "percent": 13.8474}, {"name": "Agricultural Raw Materials", "id": "AgrRaw", "percent": 1.6063}, {"name": "Metals", "id": "72-83_Metals", "percent": 6.2888}, {"name": "Fuels", "id": "27-27_Fuels", "percent": 0.7024}, {"name": "Machinery and Transport Equipment", "id": "Transp", "percent": 23.6894}, {"name": "Fuel", "id": "Fuels", "percent": 0.4709}, {"name": "Hides and Skins", "id": "41-43_HidesSkin", "percent": 0.1286}, {"name": "Raw materials", "id": "UNCTAD-SoP1", "percent": 4.9307}, {"name": "Transportation", "id": "86-89_Transport", "percent": 9.7674}, {"name": "Vegetable", "id": "06-15_Vegetable", "percent": 11.7881}, {"name": "Minerals", "id": "25-26_Minerals", "percent": 3.4216}, {"name": "Capital goods", "id": "UNCTAD-SoP4", "percent": 18.2899}, {"name": "Stone and Glass", "id": "68-71_StoneGlas", "percent": 1.7095}, {"name": "Consumer goods", "id": "UNCTAD-SoP3", "percent": 43.8258}, {"name": "Food", "id": "Food", "percent": 32.2613}, {"name": "Chemical", "id": "Chemical", "percent": 4.8818}, {"name": "Intermediate goods", "id": "UNCTAD-SoP2", "percent": 17.6863}, {"name": "Wood", "id": "44-49_Wood", "percent": 1.8572}], "exports": [{"name": "Manufactures", "id": "manuf", "percent": 10.3625}, {"name": "Food Products", "id": "16-24_FoodProd", "percent": 84.3477}, {"name": "Miscellaneous", "id": "90-99_Miscellan", "percent": 1.0852}, {"name": "Chemicals", "id": "28-38_Chemicals", "percent": 0.0032}, {"name": "Animal", "id": "01-05_Animal", "percent": 0.2768}, {"name": "Ores and Metals", "id": "OresMtls", "percent": 1.1006}, {"name": "Footwear", "id": "64-67_Footwear", "percent": 0.0071}, {"name": "Textiles and Clothing", "id": "50-63_TextCloth", "percent": 0.189}, {"name": "All Products", "id": "Total", "percent": 100}, {"name": "Plastic or Rubber", "id": "39-40_PlastiRub", "percent": 0.041}, {"name": "Textiles", "id": "Textiles", "percent": 0.1893}, {"name": "Mach and Elec", "id": "84-85_MachElec", "percent": 7.5802}, {"name": "Agricultural Raw Materials", "id": "AgrRaw", "percent": 0.0885}, {"name": "Metals", "id": "72-83_Metals", "percent": 1.5356}, {"name": "Machinery and Transport Equipment", "id": "Transp", "percent": 8.2579}, {"name": "Fuel", "id": "Fuels", "percent": 0.0012}, {"name": "Hides and Skins", "id": "41-43_HidesSkin", "percent": 0.0027}, {"name": "Raw materials", "id": "UNCTAD-SoP1", "percent": 85.9185}, {"name": "Transportation", "id": "86-89_Transport", "percent": 0.9139}, {"name": "Vegetable", "id": "06-15_Vegetable", "percent": 3.8334}, {"name": "Capital goods", "id": "UNCTAD-SoP4", "percent": 7.5603}, {"name": "Stone and Glass", "id": "68-71_StoneGlas", "percent": 0.1158}, {"name": "Consumer goods", "id": "UNCTAD-SoP3", "percent": 5.9122}, {"name": "Food", "id": "Food", "percent": 88.4472}, {"name": "Chemical", "id": "Chemical", "percent": 0.0219}, {"name": "Intermediate goods", "id": "UNCTAD-SoP2", "percent": 0.6092}, {"name": "Wood", "id": "44-49_Wood", "percent": 0.0686}]}]}